{
	"configurations" : 
	[
		{
			"directories" : 
			[
				{
					"build" : ".",
					"hasInstallRule" : true,
					"jsonFile" : "directory-.-6418b1293e1ff3d24ac9.json",
					"minimumCMakeVersion" : 
					{
						"string" : "3.12"
					},
					"projectIndex" : 0,
					"source" : ".",
					"targetIndexes" : 
					[
						0,
						1,
						2
					]
				}
			],
			"name" : "",
			"projects" : 
			[
				{
					"directoryIndexes" : 
					[
						0
					],
					"name" : "my_pkg1",
					"targetIndexes" : 
					[
						0,
						1,
						2
					]
				}
			],
			"targets" : 
			[
				{
					"directoryIndex" : 0,
					"id" : "my_node::@6890427a1f51a3e7e1df",
					"jsonFile" : "target-my_node-e39b914854c0db0d0481.json",
					"name" : "my_node",
					"projectIndex" : 0
				},
				{
					"directoryIndex" : 0,
					"id" : "my_pkg1_uninstall::@6890427a1f51a3e7e1df",
					"jsonFile" : "target-my_pkg1_uninstall-cf39366222f04153d108.json",
					"name" : "my_pkg1_uninstall",
					"projectIndex" : 0
				},
				{
					"directoryIndex" : 0,
					"id" : "uninstall::@6890427a1f51a3e7e1df",
					"jsonFile" : "target-uninstall-9ee0a9e63a16ed631743.json",
					"name" : "uninstall",
					"projectIndex" : 0
				}
			]
		}
	],
	"kind" : "codemodel",
	"paths" : 
	{
		"build" : "/home/emsi/rob2_ws/src/build/my_pkg1",
		"source" : "/home/emsi/rob2_ws/src/my_pkg1"
	},
	"version" : 
	{
		"major" : 2,
		"minor" : 3
	}
}
